mypackage/__init__.py
mypackage/main.py
mypackage/my_module.py
pptemplate-1.0.3.dist-info/LICENSE
pptemplate-1.0.3.dist-info/METADATA
pptemplate-1.0.3.dist-info/WHEEL
pptemplate-1.0.3.dist-info/top_level.txt
pptemplate-1.0.3.dist-info/RECORD
