Metadata-Version: 2.1
Name: pptemplate
Version: 1.0.3
Summary: This is a template project for python. You can change it on will to match your requirements
Author: Naser Derakhshan
Author-email: n.derakhshan@oxolo.com
License-File: LICENSE
Requires-Dist: ConfigArgParse (==1.5.3)
Requires-Dist: numpy (==1.22.3)
